local_llm_function_calling/__init__.py
local_llm_function_calling/constrainer.py
local_llm_function_calling/exceptions.py
local_llm_function_calling/generator.py
local_llm_function_calling/model/__init__.py
local_llm_function_calling/model/common.py
local_llm_function_calling/model/huggingface.py
local_llm_function_calling/model/llama.py
local_llm_function_calling/prompter.py
local_llm_function_calling/prompters/__init__.py
local_llm_function_calling/prompters/llama_function_calling.py
local_llm_function_calling/py.typed
local_llm_function_calling-0.1.23.dist-info/LICENSE
local_llm_function_calling-0.1.23.dist-info/METADATA
local_llm_function_calling-0.1.23.dist-info/WHEEL
local_llm_function_calling-0.1.23.dist-info/RECORD
