Metadata-Version: 2.1
Name: local-llm-function-calling
Version: 0.1.23
Summary: A tool for generating function arguments and choosing what function to call with local LLMs
Home-page: https://github.com/rizerphe/local-llm-function-calling
License: MIT
Keywords: llm,jsonschema,huggingface,transformers,local,llama.cpp
Author: rizerphe
Author-email: 44440399+rizerphe@users.noreply.github.com
Requires-Python: >=3.11,<4.0
Classifier: License :: OSI Approved :: MIT License
Classifier: Programming Language :: Python :: 3
Classifier: Programming Language :: Python :: 3.11
Provides-Extra: llama-cpp
Requires-Dist: json-schema-enforcer (>=0.1.3,<0.2.0)
Requires-Dist: llama-cpp-python (>=0.1.83,<0.2.0) ; extra == "llama-cpp"
Requires-Dist: torch (>=2.0.1,<3.0.0)
Requires-Dist: transformers (>=4.30.2,<5.0.0)
Project-URL: Documentation, https://local-llm-function-calling.readthedocs.io/
